i_art/__init__.py
i_art/iartest.py
py_i_art-0.1.1.dist-info/LICENSE
py_i_art-0.1.1.dist-info/METADATA
py_i_art-0.1.1.dist-info/WHEEL
py_i_art-0.1.1.dist-info/top_level.txt
py_i_art-0.1.1.dist-info/RECORD
