Metadata-Version: 2.1
Name: py-i-art
Version: 0.1.1
Summary: I-ART: A Generalized Framework for Imputation-Assisted Randomization Tests
Home-page: https://github.com/Imputation-Assisted-Randomization-Tests/py-I-ART
Author: Siyu Heng, Jiawei Zhang, and Yang Feng
Author-email: 
License: UNKNOWN
Platform: UNKNOWN
Classifier: Development Status :: 3 - Alpha
Classifier: Intended Audience :: Developers
Classifier: License :: OSI Approved :: MIT License
Classifier: Programming Language :: Python :: 3
Classifier: Programming Language :: Python :: 3.8
Requires-Python: >=3.8
Requires-Dist: mv-laplace
Requires-Dist: pandas
Requires-Dist: numpy
Requires-Dist: scikit-learn
Requires-Dist: xgboost
Requires-Dist: statsmodels
Requires-Dist: lightgbm
